mflash/__init__.py
mflash/main.py
mflash/progressbar.py
mflash/terminal.py
mflash/flashloader/ramcode/mx1270.elf
mflash/flashloader/ramcode/mx1290.elf
mflash/flashloader/ramcode/mx1300.elf
mflash/flashloader/ramcode/mx1310.elf
mflash/flashloader/ramcode/mx1350.elf
mflash/flashloader/ramcode/rtl8762c.elf
mflash/flashloader/scripts/cmd.tcl
mflash/flashloader/scripts/flash.tcl
mflash/interface/jlink_swd.cfg
mflash/interface/mxlink.cfg
mflash/interface/stlink-v2-1.cfg
mflash/interface/stlink-v2.cfg
mflash/interface/swj-dp.tcl
mflash/openocd/osx/libftdi1.2.dylib
mflash/openocd/osx/libhidapi.0.dylib
mflash/openocd/osx/libusb-0.1.4.dylib
mflash/openocd/osx/libusb-1.0.0.dylib
mflash/openocd/osx/openocd_mxos
mflash/openocd/osx/openocd_mxos_dirname
mflash/openocd/osx/openocd_mxos_run
mflash/openocd/win/libftdi1.dll
mflash/openocd/win/libhidapi-0.dll
mflash/openocd/win/libusb-0-1-4.dll
mflash/openocd/win/libusb-1.0.dll
mflash/openocd/win/openocd_mxos.exe
mflash/targets/mx1270.cfg
mflash/targets/mx1290.cfg
mflash/targets/mx1300.cfg
mflash/targets/mx1310.cfg
mflash/targets/mx1350.cfg
mflash/targets/rtl8762c.cfg
mflash-1.3.0.dist-info/LICENSE.txt
mflash-1.3.0.dist-info/METADATA
mflash-1.3.0.dist-info/WHEEL
mflash-1.3.0.dist-info/entry_points.txt
mflash-1.3.0.dist-info/top_level.txt
mflash-1.3.0.dist-info/RECORD
