Metadata-Version: 2.1
Name: mflash
Version: 1.3.0
Summary: MXCHIP Flash Tool
Home-page: https://github.com/smartsnow/mflash
Author: Snow Yang
Author-email: yangsw@mxchip.com
Keywords: MXCHIP Flash Tool
Classifier: Development Status :: 4 - Beta
Classifier: Intended Audience :: Developers
Classifier: Topic :: Software Development :: Build Tools
Classifier: Programming Language :: Python :: 3.5
Classifier: Programming Language :: Python :: 3.6
Classifier: Programming Language :: Python :: 3.7
Requires-Python: >=3.5
License-File: LICENSE.txt
